babip/__init__.py
babip/hyperopt/__init__.py
babip/hyperopt/hyperopt.py
babip/koda/__init__.py
babip/koda/koda.py
babip/koda/wordnet.pickle
babip/overfit/__init__.py
babip/overfit/overfit.py
babip/rec/__init__.py
babip/rec/rec.py
babip/rec/stopwords.txt
BABIP-0.0.1.dist-info/METADATA
BABIP-0.0.1.dist-info/WHEEL
BABIP-0.0.1.dist-info/top_level.txt
BABIP-0.0.1.dist-info/RECORD
